mlpotentials/__init__.py
mlpotentials-0.0.1.dist-info/licenses/LICENSE
mlpotentials-0.0.1.dist-info/METADATA
mlpotentials-0.0.1.dist-info/WHEEL
mlpotentials-0.0.1.dist-info/entry_points.txt
mlpotentials-0.0.1.dist-info/top_level.txt
mlpotentials-0.0.1.dist-info/RECORD
